taskscheduler/__init__.py
taskscheduler/app.py
taskscheduler/task.py
taskscheduler/ui.py
task_scheduler_by_khealpy08-1.0.0.dist-info/LICENSE.txt
task_scheduler_by_khealpy08-1.0.0.dist-info/METADATA
task_scheduler_by_khealpy08-1.0.0.dist-info/WHEEL
task_scheduler_by_khealpy08-1.0.0.dist-info/top_level.txt
task_scheduler_by_khealpy08-1.0.0.dist-info/RECORD
