Metadata-Version: 2.1
Name: task_scheduler_by_khealpy08
Version: 1.0.0
Summary: A Task Scheduler application
Home-page: https://github.com/Khealgit08/taskscheduler
Author: Michael Castil
Author-email: castilmichael08@gmail.com
License: MIT
Classifier: License :: OSI Approved :: MIT License
Classifier: Programming Language :: Python :: 3.7
Classifier: Programming Language :: Python :: 3.8
Classifier: Programming Language :: Python :: 3.9
Classifier: Programming Language :: Python :: 3.10
Classifier: Programming Language :: Python :: 3.11
Classifier: Operating System :: OS Independent
Requires-Python: >=3.7
License-File: LICENSE.txt
Requires-Dist: tkcalendar<2.0,>=1.6.1
Provides-Extra: dev
Requires-Dist: pytest>=7.0; extra == "dev"
Requires-Dist: bson>=0.5.10; extra == "dev"
Requires-Dist: twine>=4.0.2; extra == "dev"
